actchain/__init__.py
actchain/apis.py
actchain/chains/__init__.py
actchain/chains/base.py
actchain/chains/flow.py
actchain/chains/function.py
actchain/chains/junction.py
actchain/chains/loop.py
actchain/chains/pass_through.py
actchain/chains/sampling.py
actchain/event.py
actchain/exceptions.py
actchain/function.py
actchain/loop.py
actchain/singleton.py
actchain-0.1.2.dist-info/METADATA
actchain-0.1.2.dist-info/WHEEL
actchain-0.1.2.dist-info/RECORD
