Metadata-Version: 2.1
Name: actchain
Version: 0.1.2
Summary: Asynchronous Crypt Trading Chain: A toolkit for building cryptocurrency trading bots with asynchrnous loosely-couplled modules.
Home-page: https://github.com/ko0hi/actchain
License: MIT
Author: ko0hi
Author-email: ko0hi.4731@gmail.com
Requires-Python: >=3.11,<4.0
Classifier: License :: OSI Approved :: MIT License
Classifier: Programming Language :: Python :: 3
Classifier: Programming Language :: Python :: 3.11
Requires-Dist: loguru (>=0.7.2,<0.8.0)
Project-URL: Repository, https://github.com/ko0hi/actchain
